[



    {
        "id": 2,
        "name": "Pulsera",
        "price": 27,
        "mat": "Cover gold",
        "img": "",
        "quantity": 1,
        "quanty": 1
    
    },

    {
        "id": 3,
        "name": "Collar",
        "price": 20,
        "mat": "Gold",
        "img": "",
        "quantity": 1,
        "quanty": 1
    },

    {
        "id": 4,
        "name": "Topitos de arcoiris laminado",
        "price": 30,
        "mat": "Acero",
        "img": "",
        "quantity": 1,
        "quanty": 1
    },

    {
        "id": 5,
        "name": "Top",
        "price": 89,
        "mat": "Acero",
        "img": "",
        "quantity": 1,
        "quanty": 1
    },

    {
        "id": 6,
        "name": "uno",
        "price": 20,
        "mat": "Acero",
        "img": "",
        "quantity": 1,
        "quanty": 1
    },

    {
        "id": 7,
        "name": "Pulsera",
        "price": 27,
        "mat": "Cover gold",
        "img": "",
        "quantity": 1,
        "quanty": 1
    
    },

    {
        "id": 8,
        "name": "Collar",
        "price": 20,
        "mat": "Gold",
        "img": "",
        "quantity": 1,
        "quanty": 1
    },

    {
        "id": 9,
        "name": "",
        "price": 30,
        "mat": "Acero",
        "img": "",
        "quantity": 1,
        "quanty": 1
    },

    {
        "id": 10,
        "name": "Topitos",
        "price": 89,
        "mat": "Acero",
        "img": "",
        "quantity": 1,
        "quanty": 1
    }


]